codeprojectai/__init__.py
codeprojectai/core.py
tests/__init__.py
tests/test_core.py
codeproject_ai_api-0.1.dist-info/LICENSE
codeproject_ai_api-0.1.dist-info/METADATA
codeproject_ai_api-0.1.dist-info/WHEEL
codeproject_ai_api-0.1.dist-info/top_level.txt
codeproject_ai_api-0.1.dist-info/RECORD
